{
  "open_trade": {
    "coin": "SOL",
    "entry_time": "2026-07-06T13:13:07.708295+00:00",
    "key_signals": [
      {
        "source": "Fear_Greed",
        "signal_type": "sentiment",
        "description": "Extreme Fear at 24 but improving from 19.3 weekly average signals potential sentiment bottom \u2014 historically one of the strongest contrarian buy indicators."
      },
      {
        "source": "CoinTelegraph",
        "signal_type": "news",
        "description": "$60.4K flagged as 'most important area' for Bitcoin \u2014 BTC holding above this level is critical for any altcoin long thesis."
      },
      {
        "source": "Blockworks",
        "signal_type": "news",
        "description": "ETH derivatives reset and positive inflation outlook narrative supports a risk-on rotation into quality altcoins like SOL."
      },
      {
        "source": "volume_breakout",
        "signal_type": "technical",
        "description": "SOL has $1.9B in 24h volume \u2014 by far the highest liquidity among swing candidates, ensuring clean entries and exits."
      },
      {
        "source": "CoinDesk",
        "signal_type": "macro",
        "description": "U.S. inflation outlook underpins bitcoin bulls \u2014 macro tailwind supports broader crypto recovery from fear levels."
      }
    ],
    "confidence": 52
  },
  "signal_stats": {
    "Fear_Greed__sentiment": {
      "source": "Fear_Greed",
      "signal_type": "sentiment",
      "wins": 1,
      "losses": 0,
      "total": 1,
      "win_rate": 1.0,
      "total_pct": 11.82,
      "avg_return": 11.82,
      "last_seen": "2026-07-06T04:09:50.313763+00:00"
    },
    "CoinDesk__news": {
      "source": "CoinDesk",
      "signal_type": "news",
      "wins": 1,
      "losses": 0,
      "total": 1,
      "win_rate": 1.0,
      "total_pct": 11.82,
      "avg_return": 11.82,
      "last_seen": "2026-07-06T04:09:50.313779+00:00"
    },
    "CoinTelegraph__onchain": {
      "source": "CoinTelegraph",
      "signal_type": "onchain",
      "wins": 1,
      "losses": 0,
      "total": 1,
      "win_rate": 1.0,
      "total_pct": 11.82,
      "avg_return": 11.82,
      "last_seen": "2026-07-06T04:09:50.313787+00:00"
    },
    "volume_breakout__technical": {
      "source": "volume_breakout",
      "signal_type": "technical",
      "wins": 1,
      "losses": 0,
      "total": 1,
      "win_rate": 1.0,
      "total_pct": 11.82,
      "avg_return": 11.82,
      "last_seen": "2026-07-06T04:09:50.313794+00:00"
    },
    "Blockworks__macro": {
      "source": "Blockworks",
      "signal_type": "macro",
      "wins": 1,
      "losses": 0,
      "total": 1,
      "win_rate": 1.0,
      "total_pct": 11.82,
      "avg_return": 11.82,
      "last_seen": "2026-07-06T04:09:50.313801+00:00"
    }
  },
  "trade_count": 1,
  "last_updated": "2026-07-06T13:13:07.708302+00:00"
}