[
  {
    "ts": "2026-06-17T23:41:34.521081+00:00",
    "coin": "BTC",
    "price": 64381,
    "signal": "HOLD",
    "confidence": 0,
    "score": null,
    "fg": 22,
    "btc_price": 64381,
    "btc_dominance": 56.1,
    "candidates": [
      "HYPE",
      "ADA",
      "ZEC",
      "BTC",
      "XMR"
    ],
    "alert": null
  },
  {
    "ts": "2026-06-17T23:43:36.769713+00:00",
    "coin": "BTC",
    "price": 64371,
    "signal": "HOLD",
    "confidence": 0,
    "score": null,
    "fg": 22,
    "btc_price": 64371,
    "btc_dominance": 56.1,
    "candidates": [
      "HYPE",
      "ADA",
      "ZEC",
      "BTC",
      "XLM"
    ],
    "alert": null
  },
  {
    "ts": "2026-07-15T20:00:04.412168+00:00",
    "coin": "ETH",
    "price": 1923.68,
    "signal": "BUY",
    "confidence": 68,
    "score": 1.35,
    "fg": 25,
    "btc_price": 64935,
    "btc_dominance": 56.3,
    "candidates": [
      "MON",
      "USDG",
      "DEXE",
      "PUMP",
      "ETHFI",
      "LDO",
      "VIRTUAL",
      "ETH",
      "GRASS"
    ],
    "alert": "Extreme Fear improving + BTC breaking 3-week highs \u2014 historically this combination precedes 2-4 week relief rallies in ETH."
  },
  {
    "ts": "2026-07-15T21:06:17.177993+00:00",
    "coin": "ETH",
    "price": 1923.38,
    "signal": "BUY",
    "confidence": 62,
    "score": 0.55,
    "fg": 25,
    "btc_price": 64929,
    "btc_dominance": 56.3,
    "candidates": [
      "MON",
      "KITE",
      "USDG",
      "DEXE",
      "PUMP",
      "ETHFI",
      "VVV",
      "ETH",
      "GRASS"
    ],
    "alert": "Extreme Fear environment \u2014 position size conservatively and honor stop-losses strictly."
  },
  {
    "ts": "2026-07-15T22:06:17.195939+00:00",
    "coin": "ETH",
    "price": 1921.67,
    "signal": "BUY",
    "confidence": 62,
    "score": 0.55,
    "fg": 25,
    "btc_price": 64800,
    "btc_dominance": 56.2,
    "candidates": [
      "MON",
      "USDG",
      "ONDO",
      "DEXE",
      "PUMP",
      "ETHFI",
      "ZRO",
      "ETH",
      "GRASS"
    ],
    "alert": "Extreme Fear environment \u2014 position size conservatively and honor stop-losses strictly."
  },
  {
    "ts": "2026-07-15T23:06:17.235734+00:00",
    "coin": "ETH",
    "price": 1924.58,
    "signal": "BUY",
    "confidence": 62,
    "score": 0.55,
    "fg": 25,
    "btc_price": 64867,
    "btc_dominance": 56.2,
    "candidates": [
      "KITE",
      "MON",
      "USDG",
      "DEXE",
      "PUMP",
      "ETHFI",
      "ONDO",
      "ETH",
      "GRASS"
    ],
    "alert": null
  },
  {
    "ts": "2026-07-16T00:06:17.173982+00:00",
    "coin": "ETH",
    "price": 1920.22,
    "signal": "BUY",
    "confidence": 62,
    "score": 0.45,
    "fg": 25,
    "btc_price": 64773,
    "btc_dominance": 56.2,
    "candidates": [
      "MON",
      "USDG",
      "ONDO",
      "DEXE",
      "PUMP",
      "ETHFI",
      "ZRO",
      "ETH",
      "GRASS"
    ],
    "alert": "Extreme Fear persists \u2014 size positions conservatively and honor stop-losses strictly."
  },
  {
    "ts": "2026-07-16T01:06:17.419568+00:00",
    "coin": "ETH",
    "price": 1914.17,
    "signal": "BUY",
    "confidence": 62,
    "score": 0.55,
    "fg": 25,
    "btc_price": 64561,
    "btc_dominance": 56.2,
    "candidates": [
      "MON",
      "USDG",
      "DEXE",
      "ETHFI",
      "ONDO",
      "ZRO",
      "PUMP",
      "ETH",
      "GRASS"
    ],
    "alert": "Extreme Fear at 25 \u2014 historically a zone where bounces begin, but also where capitulation accelerates. Size positions conservatively."
  },
  {
    "ts": "2026-07-16T02:06:17.236634+00:00",
    "coin": "ETH",
    "price": 1920.12,
    "signal": "BUY",
    "confidence": 62,
    "score": 0.55,
    "fg": 25,
    "btc_price": 64638,
    "btc_dominance": 56.2,
    "candidates": [
      "MON",
      "USDG",
      "ONDO",
      "DEXE",
      "ZRO",
      "ETHFI",
      "LDO",
      "ETH",
      "GRASS"
    ],
    "alert": "Extreme Fear at 25 \u2014 historically a high-probability zone for mean-reversion trades in major assets."
  },
  {
    "ts": "2026-07-16T03:06:17.094505+00:00",
    "coin": "ETH",
    "price": 1923.07,
    "signal": "BUY",
    "confidence": 62,
    "score": 1.2,
    "fg": 25,
    "btc_price": 64565,
    "btc_dominance": 56.1,
    "candidates": [
      "MON",
      "USDG",
      "ONDO",
      "DEXE",
      "LDO",
      "ETHFI",
      "ZRO",
      "ETH",
      "GRASS"
    ],
    "alert": "Extreme Fear persists \u2014 position sizing should be conservative. DeFi oracle exploits are ongoing, adding systemic risk."
  },
  {
    "ts": "2026-07-16T04:06:17.159682+00:00",
    "coin": "ETH",
    "price": 1916.78,
    "signal": "BUY",
    "confidence": 62,
    "score": 0.45,
    "fg": 25,
    "btc_price": 64571,
    "btc_dominance": 56.2,
    "candidates": [
      "MON",
      "USDG",
      "DEXE",
      "ONDO",
      "ZRO",
      "ETHFI",
      "BONK",
      "ETH",
      "GRASS"
    ],
    "alert": null
  },
  {
    "ts": "2026-07-16T05:06:17.222770+00:00",
    "coin": "ETH",
    "price": 1917.2,
    "signal": "BUY",
    "confidence": 62,
    "score": 0.55,
    "fg": 25,
    "btc_price": 64581,
    "btc_dominance": 56.2,
    "candidates": [
      "DEXE",
      "MON",
      "USDG",
      "ONDO",
      "ETHFI",
      "LDO",
      "ZRO",
      "ETH",
      "GRASS"
    ],
    "alert": "Extreme Fear at 25 \u2014 historically a zone where quality assets bottom. ETH institutional flows provide conviction."
  },
  {
    "ts": "2026-07-16T06:06:17.129749+00:00",
    "coin": "ETH",
    "price": 1923.41,
    "signal": "BUY",
    "confidence": 62,
    "score": 0.55,
    "fg": 25,
    "btc_price": 64846,
    "btc_dominance": 56.2,
    "candidates": [
      "MON",
      "USDG",
      "DEXE",
      "ONDO",
      "ZRO",
      "LDO",
      "BONK",
      "ETH",
      "GRASS"
    ],
    "alert": "ETH outperforming BTC by 3x this week on ETF inflows \u2014 potential trend shift from BTC dominance to ETH leadership"
  },
  {
    "ts": "2026-07-16T07:06:17.542347+00:00",
    "coin": "ETH",
    "price": 1919.56,
    "signal": "BUY",
    "confidence": 62,
    "score": 0.55,
    "fg": 25,
    "btc_price": 64690,
    "btc_dominance": 56.2,
    "candidates": [
      "MON",
      "ONDO",
      "ZRO",
      "GNO",
      "LDO",
      "DEXE",
      "ETHFI",
      "ETH",
      "GRASS"
    ],
    "alert": "BlackRock ETF driving major ETH inflows \u2014 institutional accumulation during extreme fear is a historically strong signal."
  },
  {
    "ts": "2026-07-16T08:06:17.248956+00:00",
    "coin": "ETH",
    "price": 1908.77,
    "signal": "BUY",
    "confidence": 62,
    "score": 0.55,
    "fg": 25,
    "btc_price": 64143,
    "btc_dominance": 56.1,
    "candidates": [
      "MON",
      "USDG",
      "ONDO",
      "ZRO",
      "LDO",
      "BONK",
      "ETHFI",
      "ETH",
      "GRASS"
    ],
    "alert": "ETH outperforming BTC by 7x this week on ETF inflows \u2014 watch for momentum continuation or exhaustion at $1,950-$2,000 resistance zone."
  },
  {
    "ts": "2026-07-16T09:06:17.249314+00:00",
    "coin": "LDO",
    "price": 0.364668,
    "signal": "BUY",
    "confidence": 58,
    "score": 0.45,
    "fg": 25,
    "btc_price": 64089,
    "btc_dominance": 56.2,
    "candidates": [
      "MON",
      "ONDO",
      "BONK",
      "ZRO",
      "LDO",
      "ETHFI",
      "DEXE",
      "ETH",
      "GRASS"
    ],
    "alert": null
  },
  {
    "ts": "2026-07-16T10:06:17.215857+00:00",
    "coin": "ETH",
    "price": 1883.45,
    "signal": "BUY",
    "confidence": 62,
    "score": 0.45,
    "fg": 25,
    "btc_price": 64045,
    "btc_dominance": 56.2,
    "candidates": [
      "USDG",
      "MON",
      "ONDO",
      "ZRO",
      "BONK",
      "DEXE",
      "LDO",
      "ETH",
      "GRASS"
    ],
    "alert": "CryptoSlate reports $478M ETH buy signal forming on-chain while market sentiment sits at Extreme Fear \u2014 classic accumulation setup."
  },
  {
    "ts": "2026-07-16T11:06:17.269143+00:00",
    "coin": "ETH",
    "price": 1884.58,
    "signal": "BUY",
    "confidence": 62,
    "score": 0.45,
    "fg": 25,
    "btc_price": 64114,
    "btc_dominance": 56.2,
    "candidates": [
      "USDG",
      "ONDO",
      "MON",
      "BONK",
      "DEXE",
      "ZRO",
      "LDO",
      "ETH",
      "GRASS"
    ],
    "alert": "Extreme Fear at 25 \u2014 historically a contrarian buy zone, but requires strict stop-loss discipline."
  },
  {
    "ts": "2026-07-16T12:06:17.416256+00:00",
    "coin": "ETH",
    "price": 1881.08,
    "signal": "BUY",
    "confidence": 62,
    "score": 0.55,
    "fg": 25,
    "btc_price": 64128,
    "btc_dominance": 56.2,
    "candidates": [
      "USDG",
      "ONDO",
      "MON",
      "BONK",
      "LDO",
      "ZRO",
      "DEXE",
      "ETH",
      "GRASS"
    ],
    "alert": null
  },
  {
    "ts": "2026-07-16T13:06:17.363703+00:00",
    "coin": "ETH",
    "price": 1870.45,
    "signal": "BUY",
    "confidence": 62,
    "score": 0.45,
    "fg": 25,
    "btc_price": 63943,
    "btc_dominance": 56.2,
    "candidates": [
      "USDG",
      "DEXE",
      "BONK",
      "ONDO",
      "MON",
      "ZRO",
      "LDO",
      "ETH",
      "GRASS"
    ],
    "alert": "Extreme Fear market \u2014 position sizing should be conservative (50-75% of normal) given bearish structure across most alts."
  },
  {
    "ts": "2026-07-16T14:06:17.328486+00:00",
    "coin": "ETH",
    "price": 1882.03,
    "signal": "BUY",
    "confidence": 58,
    "score": 0.35,
    "fg": 25,
    "btc_price": 64332,
    "btc_dominance": 56.2,
    "candidates": [
      "ONDO",
      "MON",
      "USDG",
      "DEXE",
      "LDO",
      "BONK",
      "JTO",
      "ETH",
      "GRASS"
    ],
    "alert": "Market in Extreme Fear \u2014 position sizing should be conservative. Use tight stop-loss."
  },
  {
    "ts": "2026-07-16T15:06:17.307210+00:00",
    "coin": "ETH",
    "price": 1876.98,
    "signal": "BUY",
    "confidence": 62,
    "score": 0.45,
    "fg": 25,
    "btc_price": 64427,
    "btc_dominance": 56.3,
    "candidates": [
      "DEXE",
      "MON",
      "ONDO",
      "LDO",
      "USDG",
      "BONK",
      "JTO",
      "ETH",
      "GRASS"
    ],
    "alert": null
  },
  {
    "ts": "2026-07-16T16:06:17.392936+00:00",
    "coin": "ETH",
    "price": 1876.88,
    "signal": "BUY",
    "confidence": 62,
    "score": 0.55,
    "fg": 25,
    "btc_price": 64552,
    "btc_dominance": 56.4,
    "candidates": [
      "DEXE",
      "ONDO",
      "MON",
      "LDO",
      "USDG",
      "JTO",
      "BONK",
      "ETH",
      "GRASS"
    ],
    "alert": null
  },
  {
    "ts": "2026-07-16T17:06:17.355455+00:00",
    "coin": "ETH",
    "price": 1874.84,
    "signal": "BUY",
    "confidence": 62,
    "score": 0.55,
    "fg": 25,
    "btc_price": 64327,
    "btc_dominance": 56.3,
    "candidates": [
      "DEXE",
      "ONDO",
      "MON",
      "BONK",
      "USDG",
      "LDO",
      "PYTH",
      "ETH",
      "GRASS"
    ],
    "alert": "Extreme Fear at 25 \u2014 historically a zone where swing trade entries outperform, but position sizing should be conservative."
  },
  {
    "ts": "2026-07-16T18:06:17.267471+00:00",
    "coin": "ETH",
    "price": 1868.82,
    "signal": "BUY",
    "confidence": 58,
    "score": 0.35,
    "fg": 25,
    "btc_price": 64051,
    "btc_dominance": 56.3,
    "candidates": [
      "DEXE",
      "MON",
      "ONDO",
      "BONK",
      "USDG",
      "JTO",
      "PYTH",
      "ETH",
      "LDO",
      "GRASS"
    ],
    "alert": "Market in Extreme Fear \u2014 position sizing should be conservative; only risk capital you can afford to lose on this counter-trend setup."
  },
  {
    "ts": "2026-07-16T19:06:17.500607+00:00",
    "coin": "ETH",
    "price": 1875.35,
    "signal": "BUY",
    "confidence": 62,
    "score": 0.45,
    "fg": 25,
    "btc_price": 64242,
    "btc_dominance": 56.3,
    "candidates": [
      "DEXE",
      "BONK",
      "MON",
      "ONDO",
      "USDG",
      "JTO",
      "PYTH",
      "ETH",
      "LDO",
      "GRASS"
    ],
    "alert": "Extreme Fear (25) combined with massive institutional catalysts creates a high-probability mean reversion setup for ETH."
  },
  {
    "ts": "2026-07-16T20:06:17.327514+00:00",
    "coin": "ETH",
    "price": 1872.75,
    "signal": "BUY",
    "confidence": 62,
    "score": 0.55,
    "fg": 25,
    "btc_price": 64184,
    "btc_dominance": 56.3,
    "candidates": [
      "DEXE",
      "MON",
      "BONK",
      "ONDO",
      "JTO",
      "KITE",
      "LDO",
      "ETH",
      "GRASS"
    ],
    "alert": null
  },
  {
    "ts": "2026-07-16T21:06:17.453039+00:00",
    "coin": "ETH",
    "price": 1873.04,
    "signal": "BUY",
    "confidence": 58,
    "score": 0.45,
    "fg": 25,
    "btc_price": 64091,
    "btc_dominance": 56.3,
    "candidates": [
      "DEXE",
      "MON",
      "BONK",
      "USDG",
      "PYTH",
      "PUMP",
      "JTO",
      "ETH",
      "LDO",
      "GRASS"
    ],
    "alert": "Market in Extreme Fear \u2014 high-conviction contrarian setups available but position sizing should be conservative."
  },
  {
    "ts": "2026-07-16T22:06:17.180216+00:00",
    "coin": "ETH",
    "price": 1879.04,
    "signal": "BUY",
    "confidence": 62,
    "score": 0.45,
    "fg": 25,
    "btc_price": 64147,
    "btc_dominance": 56.2,
    "candidates": [
      "DEXE",
      "MON",
      "BONK",
      "PYTH",
      "PUMP",
      "KITE",
      "VIRTUAL",
      "ETH",
      "LDO",
      "GRASS"
    ],
    "alert": null
  },
  {
    "ts": "2026-07-16T23:06:17.785106+00:00",
    "coin": "ETH",
    "price": 1866.25,
    "signal": "BUY",
    "confidence": 62,
    "score": 0.45,
    "fg": 25,
    "btc_price": 63895,
    "btc_dominance": 56.3,
    "candidates": [
      "DEXE",
      "USDG",
      "JTO",
      "MON",
      "BONK",
      "AAVE",
      "PYTH",
      "ETH",
      "LDO",
      "GRASS"
    ],
    "alert": null
  },
  {
    "ts": "2026-07-17T00:06:17.731288+00:00",
    "coin": "ETH",
    "price": 1862.6,
    "signal": "BUY",
    "confidence": 58,
    "score": 0.35,
    "fg": 27,
    "btc_price": 63744,
    "btc_dominance": 56.3,
    "candidates": [
      "DEXE",
      "USDG",
      "BONK",
      "JTO",
      "MON",
      "HYPE",
      "PYTH",
      "ETH",
      "LDO",
      "GRASS"
    ],
    "alert": "Market fear at 27 \u2014 oversold RSI signals are historically our most reliable entry indicator (80% win rate). Proceed with tight risk management."
  }
]